<?xml version="1.0" encoding="UTF-8"?>
<con:soapui-project id="4d6d8e1a-23a5-4df2-ab06-6e2c63ed9091" activeEnvironment="Default" name="REST Final Project" resourceRoot="" soapui-version="5.6.0" xmlns:con="http://eviware.com/soapui/config"><con:settings/><con:interface xsi:type="con:RestService" id="18289536-dc4b-4eb1-8777-51fea0aff66b" wadlVersion="http://wadl.dev.java.net/2009/02" name="http://rest-api.upskills.in" type="rest" xmlns:xsi="http://www.w3.org/2001/XMLSchema-instance"><con:settings/><con:definitionCache type="TEXT" rootPart=""/><con:endpoints><con:endpoint>http://rest-api.upskills.in</con:endpoint></con:endpoints><con:resource name="Client_credentials" path="/api/rest_admin/oauth2/token/client_credentials" id="a6935bd4-2b23-4781-89da-eb06c0ecfe03"><con:settings/><con:parameters/><con:method name="Client_credentials 1" id="e616bf54-9d48-4cba-84e3-d0c7b1a16a04" method="POST"><con:settings/><con:parameters/><con:representation type="FAULT"><con:mediaType>application/json; charset=utf-8</con:mediaType><con:status>405</con:status><con:params/><con:element xmlns:cli="http://rest-api.upskills.in/api/rest_admin/oauth2/token/client_credentials">cli:Fault</con:element></con:representation><con:representation type="RESPONSE"><con:mediaType>application/json; charset=utf-8</con:mediaType><con:status>200</con:status><con:params/><con:element xmlns:cli="http://rest-api.upskills.in/api/rest_admin/oauth2/token/client_credentials">cli:Response</con:element></con:representation><con:representation type="REQUEST"><con:mediaType>application/json</con:mediaType><con:params/></con:representation><con:request name="Request 1" id="f62fbc77-2d01-4c0f-ac8b-643358ffb893" mediaType="application/json" postQueryString="false"><con:settings><con:setting id="com.eviware.soapui.impl.wsdl.WsdlRequest@request-headers">&lt;entry key="Authorization" value="Basic dXBza2lsbHNfcmVzdF9hZG1pbl9vYXV0aF9jbGllbnQ6dXBza2lsbHNfcmVzdF9hZG1pbl9vYXV0aF9zZWNyZXQ=" xmlns="http://eviware.com/soapui/config"/></con:setting></con:settings><con:endpoint>http://rest-api.upskills.in</con:endpoint><con:request/><con:originalUri>http://rest-api.upskills.in/api/rest_admin/oauth2/token/client_credentials</con:originalUri><con:credentials><con:authType>No Authorization</con:authType></con:credentials><con:jmsConfig JMSDeliveryMode="PERSISTENT"/><con:jmsPropertyConfig/><con:parameters/></con:request></con:method></con:resource></con:interface><con:interface xsi:type="con:RestService" id="5082b186-4b87-4fe2-b14b-9ab67d109ff6" wadlVersion="http://wadl.dev.java.net/2009/02" name="http://rest-api.upskills.in" type="rest" xmlns:xsi="http://www.w3.org/2001/XMLSchema-instance"><con:settings/><con:definitionCache type="TEXT" rootPart=""/><con:endpoints><con:endpoint>http://rest-api.upskills.in</con:endpoint></con:endpoints><con:resource name="Login" path="/api/rest_admin/login" id="e056ec4d-647b-40f5-b523-55875f1a3e68"><con:settings/><con:parameters/><con:method name="Login 1" id="9fee5317-ac87-49c1-85b9-10d62a41079d" method="POST"><con:settings/><con:parameters/><con:representation type="RESPONSE"><con:mediaType>application/json; charset=utf-8</con:mediaType><con:status>200</con:status><con:params/><con:element xmlns:log="http://rest-api.upskills.in/api/rest_admin/login">log:Response</con:element></con:representation><con:representation type="REQUEST"><con:mediaType>application/json</con:mediaType><con:params/></con:representation><con:representation type="FAULT"><con:mediaType>application/json; charset=utf-8</con:mediaType><con:status>400</con:status><con:params/><con:element xmlns:log="http://rest-api.upskills.in/api/rest_admin/login">log:Fault</con:element></con:representation><con:request name="Request 1" id="021284f2-7bc5-40f1-891c-817736d89da6" mediaType="application/json" postQueryString="false"><con:settings><con:setting id="com.eviware.soapui.impl.wsdl.WsdlRequest@request-headers">&lt;entry key="Authorization" value="Bearer 188d7d0ff0db23c603a521420a3c507a9bbd6c10" xmlns="http://eviware.com/soapui/config"/></con:setting></con:settings><con:endpoint>http://rest-api.upskills.in</con:endpoint><con:request>{
  "username": "upskills_admin",
  "password": "Talent4$$"
}</con:request><con:originalUri>http://rest-api.upskills.in/api/rest_admin/login</con:originalUri><con:credentials><con:authType>No Authorization</con:authType></con:credentials><con:jmsConfig JMSDeliveryMode="PERSISTENT"/><con:jmsPropertyConfig/><con:parameters/></con:request></con:method></con:resource></con:interface><con:interface xsi:type="con:RestService" id="74517fbf-b13f-4ed5-87d7-784b374aee5b" wadlVersion="http://wadl.dev.java.net/2009/02" name="http://rest-api.upskills.in" type="rest" xmlns:xsi="http://www.w3.org/2001/XMLSchema-instance"><con:settings/><con:definitionCache type="TEXT" rootPart=""/><con:endpoints><con:endpoint>http://rest-api.upskills.in</con:endpoint></con:endpoints><con:resource name="User" path="/api/rest_admin/user" id="5d30e893-485a-44a0-adc6-ebd6c4b0576a"><con:settings/><con:parameters/><con:method name="User 1" id="0e061bb9-9e0f-483c-9b9a-1d7a32d1427e" method="GET"><con:settings/><con:parameters/><con:representation type="RESPONSE"><con:mediaType>application/json; charset=utf-8</con:mediaType><con:status>200</con:status><con:params/><con:element xmlns:user="http://rest-api.upskills.in/api/rest_admin/user">user:Response</con:element></con:representation><con:request name="Request 1" id="5e97f26e-feab-4b25-bfa2-84e80e393777" mediaType="application/json"><con:settings><con:setting id="com.eviware.soapui.impl.wsdl.WsdlRequest@request-headers">&lt;entry key="Authorization" value="Bearer 188d7d0ff0db23c603a521420a3c507a9bbd6c10" xmlns="http://eviware.com/soapui/config"/></con:setting></con:settings><con:endpoint>http://rest-api.upskills.in</con:endpoint><con:request/><con:credentials><con:authType>No Authorization</con:authType></con:credentials><con:jmsConfig JMSDeliveryMode="PERSISTENT"/><con:jmsPropertyConfig/><con:parameters/></con:request></con:method></con:resource></con:interface><con:interface xsi:type="con:RestService" id="95e86a67-3e7f-4f23-91ab-d5a7ce79e293" wadlVersion="http://wadl.dev.java.net/2009/02" name="http://rest-api.upskills.in" type="rest" xmlns:xsi="http://www.w3.org/2001/XMLSchema-instance"><con:settings/><con:definitionCache type="TEXT" rootPart=""/><con:endpoints><con:endpoint>http://rest-api.upskills.in</con:endpoint></con:endpoints><con:resource name="Logout" path="/api/rest_admin/logout" id="a3107f32-74d1-40d0-948e-eca378bd06eb"><con:settings/><con:parameters/><con:method name="Logout 1" id="4de2388f-83d7-4f27-ba6d-68cd5c45f15c" method="POST"><con:settings/><con:parameters/><con:representation type="REQUEST"><con:mediaType>application/json</con:mediaType><con:params/></con:representation><con:representation type="RESPONSE"><con:mediaType>application/json; charset=utf-8</con:mediaType><con:status>200</con:status><con:params/><con:element xmlns:log="http://rest-api.upskills.in/api/rest_admin/logout">log:Response</con:element></con:representation><con:representation type="FAULT"><con:mediaType>application/json; charset=utf-8</con:mediaType><con:status>400</con:status><con:params/><con:element xmlns:log="http://rest-api.upskills.in/api/rest_admin/logout">log:Fault</con:element></con:representation><con:request name="Request 1" id="48d8853f-eb00-4891-b9b6-4336aaaf88de" mediaType="application/json" postQueryString="false"><con:settings><con:setting id="com.eviware.soapui.impl.wsdl.WsdlRequest@request-headers">&lt;entry key="Authorization" value="Bearer 188d7d0ff0db23c603a521420a3c507a9bbd6c10" xmlns="http://eviware.com/soapui/config"/></con:setting></con:settings><con:endpoint>http://rest-api.upskills.in</con:endpoint><con:request/><con:credentials><con:authType>No Authorization</con:authType></con:credentials><con:jmsConfig JMSDeliveryMode="PERSISTENT"/><con:jmsPropertyConfig/><con:parameters/><con:parameterOrder/></con:request></con:method></con:resource></con:interface><con:interface xsi:type="con:RestService" id="1e53b24c-2569-4c3a-b249-cca37fc9a16a" wadlVersion="http://wadl.dev.java.net/2009/02" name="http://rest-api.upskills.in" type="rest" xmlns:xsi="http://www.w3.org/2001/XMLSchema-instance"><con:settings/><con:definitionCache type="TEXT" rootPart=""/><con:endpoints><con:endpoint>http://rest-api.upskills.in</con:endpoint></con:endpoints><con:resource name="Customers" path="/api/rest_admin/customers" id="1fc40eff-fab2-46f9-b765-cb96a36429d4"><con:settings/><con:parameters/><con:method name="Customers 1" id="0f1e346a-6d36-4e71-bfba-2f765e85e648" method="POST"><con:settings/><con:parameters/><con:representation type="FAULT"><con:mediaType>application/json; charset=utf-8</con:mediaType><con:status>400</con:status><con:params/><con:element xmlns:cus="http://rest-api.upskills.in/api/rest_admin/customers">cus:Fault</con:element></con:representation><con:representation type="REQUEST"><con:mediaType>application/json</con:mediaType><con:params/></con:representation><con:representation type="RESPONSE"><con:mediaType>application/json; charset=utf-8</con:mediaType><con:status>200</con:status><con:params/><con:element xmlns:cus="http://rest-api.upskills.in/api/rest_admin/customers">cus:Response</con:element></con:representation><con:request name="AddCustomer" id="9ce7287b-ad2d-46b8-b763-8dea5e816459" mediaType="application/json" postQueryString="false"><con:settings><con:setting id="com.eviware.soapui.impl.wsdl.WsdlRequest@request-headers">&lt;xml-fragment/></con:setting></con:settings><con:endpoint>http://rest-api.upskills.in</con:endpoint><con:request>{
"firstname": "Demo",
"lastname": "User01",
"email": "demouser01@gmail.com",
"password": "password",
"confirm": "password", 
"telephone": "1-541-754-3010"
}</con:request><con:credentials><con:authType>No Authorization</con:authType></con:credentials><con:jmsConfig JMSDeliveryMode="PERSISTENT"/><con:jmsPropertyConfig/><con:parameters/></con:request></con:method></con:resource></con:interface><con:interface xsi:type="con:RestService" id="36f654f2-53a8-4e44-9f2c-4945ab7f21a5" wadlVersion="http://wadl.dev.java.net/2009/02" name="http://rest-api.upskills.in" type="rest" xmlns:xsi="http://www.w3.org/2001/XMLSchema-instance"><con:settings/><con:definitionCache type="TEXT" rootPart=""/><con:endpoints><con:endpoint>http://rest-api.upskills.in</con:endpoint></con:endpoints><con:resource name="$" path="/api/rest_admin/customers/${Properties#CustID}" id="5393624f-6db0-476f-813d-042d140e2666"><con:settings/><con:parameters/><con:method name="GetCustomerDetails" id="e0db028c-1ff0-4147-9879-4b38899dc8c3" method="GET"><con:settings/><con:parameters/><con:representation type="RESPONSE"><con:mediaType>application/json; charset=utf-8</con:mediaType><con:status>200</con:status><con:params/><con:element xmlns:cus="http://rest-api.upskills.in/api/rest_admin/customers/">cus:Response</con:element></con:representation><con:request name="Request 1" id="2874d57f-7ead-4396-94cb-422978ca4ff9" mediaType="application/json"><con:settings/><con:endpoint>http://rest-api.upskills.in</con:endpoint><con:request/><con:credentials><con:authType>No Authorization</con:authType></con:credentials><con:jmsConfig JMSDeliveryMode="PERSISTENT"/><con:jmsPropertyConfig/><con:parameters/></con:request></con:method></con:resource></con:interface><con:interface xsi:type="con:RestService" id="7a8885d9-98ce-4eca-889b-ce9167f992ba" wadlVersion="http://wadl.dev.java.net/2009/02" name="http://rest-api.upskills.in" type="rest" xmlns:xsi="http://www.w3.org/2001/XMLSchema-instance"><con:settings/><con:definitionCache type="TEXT" rootPart=""/><con:endpoints><con:endpoint>http://rest-api.upskills.in</con:endpoint></con:endpoints><con:resource name="$Properties" path="/api/rest_admin/customers/${Properties#CustID}" id="44693a04-9825-4faf-9279-cd3eedeee096"><con:settings/><con:parameters/><con:method name="ModifyCustDetails" id="aa5b2e09-83bb-40cb-b600-7e0a71959e28" method="PUT"><con:settings/><con:parameters/><con:representation type="RESPONSE"><con:mediaType>application/json; charset=utf-8</con:mediaType><con:status>200</con:status><con:params/><con:element xmlns:ns="http://rest-api.upskills.in/api/rest_admin/customers/1597">ns:Response</con:element></con:representation><con:representation type="REQUEST"><con:mediaType>application/json</con:mediaType><con:params/></con:representation><con:request name="Request 1" id="91ffd301-c8df-4a86-909a-0d2d7db75710" mediaType="application/json" postQueryString="false"><con:settings><con:setting id="com.eviware.soapui.impl.wsdl.WsdlRequest@request-headers">&lt;xml-fragment/></con:setting></con:settings><con:endpoint>http://rest-api.upskills.in</con:endpoint><con:request>{
"firstname": "Krishna Kumar",
"telephone": "0123456789"
}</con:request><con:credentials><con:authType>No Authorization</con:authType></con:credentials><con:jmsConfig JMSDeliveryMode="PERSISTENT"/><con:jmsPropertyConfig/><con:parameters/></con:request></con:method></con:resource></con:interface><con:testSuite id="e848a11c-28e8-4537-9f9c-aa62c26c33e1" name="TestSuite 1"><con:settings/><con:runType>SEQUENTIAL</con:runType><con:testCase id="e51a63fa-c680-40d4-bc27-9445559b43cc" failOnError="true" failTestCaseOnErrors="true" keepSession="false" maxResults="0" name="TC001 and TC002" searchProperties="true"><con:settings/><con:testStep type="restrequest" name="TC001-AdminGetToken" id="de9fcce2-74c1-46c9-ae66-871de62928c5"><con:settings/><con:config service="http://rest-api.upskills.in" resourcePath="/api/rest_admin/oauth2/token/client_credentials" methodName="Client_credentials 1" xsi:type="con:RestRequestStep" xmlns:xsi="http://www.w3.org/2001/XMLSchema-instance"><con:restRequest name="AdminGetToken" id="f62fbc77-2d01-4c0f-ac8b-643358ffb893" mediaType="application/json" postQueryString="false"><con:settings><con:setting id="com.eviware.soapui.impl.wsdl.WsdlRequest@request-headers">&lt;entry key="Authorization" value="Basic dXBza2lsbHNfcmVzdF9hZG1pbl9vYXV0aF9jbGllbnQ6dXBza2lsbHNfcmVzdF9hZG1pbl9vYXV0aF9zZWNyZXQ=" xmlns="http://eviware.com/soapui/config"/></con:setting></con:settings><con:endpoint>http://rest-api.upskills.in</con:endpoint><con:request/><con:originalUri>http://rest-api.upskills.in/api/rest_admin/oauth2/token/client_credentials</con:originalUri><con:assertion type="Valid HTTP Status Codes" id="46228ad7-47e0-4d3e-9d41-3c3b5a73c0e4" name="Valid HTTP Status Codes"><con:configuration><codes>200</codes></con:configuration></con:assertion><con:credentials><con:authType>No Authorization</con:authType></con:credentials><con:jmsConfig JMSDeliveryMode="PERSISTENT"/><con:jmsPropertyConfig/><con:parameters/></con:restRequest></con:config></con:testStep><con:testStep type="groovy" name="Groovy Script" id="c938cfdc-44a1-4006-9d15-69a69a6b5fd0"><con:settings/><con:config><script>
import groovy.json.JsonSlurper
def response=testRunner.testCase.getTestStepByName("TC001-AdminGetToken").getPropertyValue("response")
log.info response
def holder = new JsonSlurper().parseText(response)
def accessToken=holder.data.access_token
log.info accessToken
def completeAccessToken="bearer " +accessToken
log.info completeAccessToken
testRunner.testCase.getTestStepByName("Properties").setPropertyValue("accessToken",completeAccessToken)
</script></con:config></con:testStep><con:testStep type="properties" name="Properties" id="98a9295f-8acf-4395-a6e6-493effac1924"><con:settings/><con:config xsi:type="con:PropertiesStep" saveFirst="true" xmlns:xsi="http://www.w3.org/2001/XMLSchema-instance"><con:properties><con:property><con:name>accessToken</con:name><con:value>bearer 849f5be51d608bb65dc05676af5c83bbc5d0e5e2</con:value></con:property></con:properties></con:config></con:testStep><con:testStep type="restrequest" name="TC002-Login" id="ad78603e-6472-4c1c-bc13-1999d39a924e"><con:settings/><con:config service="http://rest-api.upskills.in" resourcePath="/api/rest_admin/login" methodName="Login 1" xsi:type="con:RestRequestStep" xmlns:xsi="http://www.w3.org/2001/XMLSchema-instance"><con:restRequest name="Login" id="021284f2-7bc5-40f1-891c-817736d89da6" mediaType="application/json" postQueryString="false"><con:settings><con:setting id="com.eviware.soapui.impl.wsdl.WsdlRequest@request-headers">&lt;entry key="Authorization" value="${Properties#accessToken}" xmlns="http://eviware.com/soapui/config"/></con:setting></con:settings><con:endpoint>http://rest-api.upskills.in</con:endpoint><con:request>{
  "username": "upskills_admin",
  "password": "Talent4$$"
}</con:request><con:originalUri>http://rest-api.upskills.in/api/rest_admin/login</con:originalUri><con:assertion type="Valid HTTP Status Codes" id="0d881bf0-282a-4b6e-b684-9befce73dbaf" name="Valid HTTP Status Codes"><con:configuration><codes>200</codes></con:configuration></con:assertion><con:credentials><con:authType>No Authorization</con:authType></con:credentials><con:jmsConfig JMSDeliveryMode="PERSISTENT"/><con:jmsPropertyConfig/><con:parameters/></con:restRequest></con:config></con:testStep><con:testStep type="restrequest" name="TC002-GetUserAccDetails" id="5b0802a0-5173-4cda-9b1d-4dcc2111bd0c"><con:settings/><con:config service="http://rest-api.upskills.in" resourcePath="/api/rest_admin/user" methodName="User 1" xsi:type="con:RestRequestStep" xmlns:xsi="http://www.w3.org/2001/XMLSchema-instance"><con:restRequest name="GetUserAccDetails" id="5e97f26e-feab-4b25-bfa2-84e80e393777" mediaType="application/json"><con:settings><con:setting id="com.eviware.soapui.impl.wsdl.WsdlRequest@request-headers">&lt;entry key="Authorization" value="${Properties#accessToken}" xmlns="http://eviware.com/soapui/config"/></con:setting></con:settings><con:endpoint>http://rest-api.upskills.in</con:endpoint><con:request/><con:originalUri>http://rest-api.upskills.in/api/rest_admin/user</con:originalUri><con:assertion type="Valid HTTP Status Codes" id="b944dc16-5d72-41dd-a575-5adf48d208c7" name="Valid HTTP Status Codes"><con:configuration><codes>200</codes></con:configuration></con:assertion><con:credentials><con:authType>No Authorization</con:authType></con:credentials><con:jmsConfig JMSDeliveryMode="PERSISTENT"/><con:jmsPropertyConfig/><con:parameters/></con:restRequest></con:config></con:testStep><con:testStep type="restrequest" name="TC002-logout" id="9d71065d-d257-4196-8df1-b1cea45e4eb3"><con:settings/><con:config service="http://rest-api.upskills.in" resourcePath="/api/rest_admin/logout" methodName="Logout 1" xsi:type="con:RestRequestStep" xmlns:xsi="http://www.w3.org/2001/XMLSchema-instance"><con:restRequest name="logout" id="48d8853f-eb00-4891-b9b6-4336aaaf88de" mediaType="application/json" postQueryString="false"><con:settings><con:setting id="com.eviware.soapui.impl.wsdl.WsdlRequest@request-headers">&lt;entry key="Authorization" value="${Properties#accessToken}" xmlns="http://eviware.com/soapui/config"/></con:setting></con:settings><con:endpoint>http://rest-api.upskills.in</con:endpoint><con:request/><con:originalUri>http://rest-api.upskills.in/api/rest_admin/logout</con:originalUri><con:assertion type="Valid HTTP Status Codes" id="dedfaca1-acfb-41a0-9f41-7ac954653ed0" name="Valid HTTP Status Codes"><con:configuration><codes>200</codes></con:configuration></con:assertion><con:credentials><con:authType>No Authorization</con:authType></con:credentials><con:jmsConfig JMSDeliveryMode="PERSISTENT"/><con:jmsPropertyConfig/><con:parameters/><con:parameterOrder/></con:restRequest></con:config></con:testStep><con:properties/></con:testCase><con:testCase id="d7a0a046-4ce0-4643-8905-1c804075236c" failOnError="true" failTestCaseOnErrors="true" keepSession="false" maxResults="0" name="TC008" searchProperties="true"><con:settings/><con:testStep type="restrequest" name="AdminGetToken" id="6bc535e2-37e9-4564-a43f-d55f105dc180"><con:settings/><con:config service="http://rest-api.upskills.in" resourcePath="/api/rest_admin/oauth2/token/client_credentials" methodName="Client_credentials 1" xsi:type="con:RestRequestStep" xmlns:xsi="http://www.w3.org/2001/XMLSchema-instance"><con:restRequest name="AdminGetToken" id="f62fbc77-2d01-4c0f-ac8b-643358ffb893" mediaType="application/json" postQueryString="false"><con:settings><con:setting id="com.eviware.soapui.impl.wsdl.WsdlRequest@request-headers">&lt;entry key="Authorization" value="Basic dXBza2lsbHNfcmVzdF9hZG1pbl9vYXV0aF9jbGllbnQ6dXBza2lsbHNfcmVzdF9hZG1pbl9vYXV0aF9zZWNyZXQ=" xmlns="http://eviware.com/soapui/config"/></con:setting></con:settings><con:endpoint>http://rest-api.upskills.in</con:endpoint><con:request/><con:originalUri>http://rest-api.upskills.in/api/rest_admin/oauth2/token/client_credentials</con:originalUri><con:assertion type="Valid HTTP Status Codes" id="46228ad7-47e0-4d3e-9d41-3c3b5a73c0e4" name="Valid HTTP Status Codes"><con:configuration><codes>200</codes></con:configuration></con:assertion><con:credentials><con:authType>No Authorization</con:authType></con:credentials><con:jmsConfig JMSDeliveryMode="PERSISTENT"/><con:jmsPropertyConfig/><con:parameters/></con:restRequest></con:config></con:testStep><con:testStep type="groovy" name="Groovy Script" id="d400c94e-3683-4129-ba36-1c48878f6b33"><con:settings/><con:config><script>
import groovy.json.JsonSlurper
def response=testRunner.testCase.getTestStepByName("AdminGetToken").getPropertyValue("response")
log.info response
def holder = new JsonSlurper().parseText(response)
def accessToken=holder.data.access_token
log.info accessToken
def completeAccessToken="bearer " +accessToken
log.info completeAccessToken
testRunner.testCase.getTestStepByName("Properties").setPropertyValue("accessToken",completeAccessToken)</script></con:config></con:testStep><con:testStep type="properties" name="Properties" id="239d281f-f0af-4aa3-a206-353effa2a572"><con:settings/><con:config xsi:type="con:PropertiesStep" saveFirst="true" xmlns:xsi="http://www.w3.org/2001/XMLSchema-instance"><con:properties><con:property><con:name>accessToken</con:name><con:value>bearer cfbd4f7feb96b735b332eeff52106f831e41557b</con:value></con:property><con:property><con:name>CustID</con:name><con:value>1598</con:value></con:property></con:properties></con:config></con:testStep><con:testStep type="restrequest" name="Login" id="733897fa-f640-41cd-89d4-ec388d1ef1de"><con:settings/><con:config service="http://rest-api.upskills.in" resourcePath="/api/rest_admin/login" methodName="Login 1" xsi:type="con:RestRequestStep" xmlns:xsi="http://www.w3.org/2001/XMLSchema-instance"><con:restRequest name="Copy of TC002-Login" id="021284f2-7bc5-40f1-891c-817736d89da6" mediaType="application/json" postQueryString="false"><con:settings><con:setting id="com.eviware.soapui.impl.wsdl.WsdlRequest@request-headers">&lt;entry key="Authorization" value="${Properties#accessToken}" xmlns="http://eviware.com/soapui/config"/></con:setting></con:settings><con:endpoint>http://rest-api.upskills.in</con:endpoint><con:request>{
  "username": "upskills_admin",
  "password": "Talent4$$"
}</con:request><con:originalUri>http://rest-api.upskills.in/api/rest_admin/login</con:originalUri><con:assertion type="Valid HTTP Status Codes" id="0d881bf0-282a-4b6e-b684-9befce73dbaf" name="Valid HTTP Status Codes"><con:configuration><codes>200</codes></con:configuration></con:assertion><con:credentials><con:authType>No Authorization</con:authType></con:credentials><con:jmsConfig JMSDeliveryMode="PERSISTENT"/><con:jmsPropertyConfig/><con:parameters/></con:restRequest></con:config></con:testStep><con:testStep type="restrequest" name="AddCustomer" id="cb251b71-1cae-450d-8cca-3419b1a5c3e5"><con:settings/><con:config service="http://rest-api.upskills.in" resourcePath="/api/rest_admin/customers" methodName="Customers 1" xsi:type="con:RestRequestStep" xmlns:xsi="http://www.w3.org/2001/XMLSchema-instance"><con:restRequest name="AddCustomer" id="9ce7287b-ad2d-46b8-b763-8dea5e816459" mediaType="application/json" postQueryString="false"><con:settings><con:setting id="com.eviware.soapui.impl.wsdl.WsdlRequest@request-headers">&lt;entry key="Authorization" value="${Properties#accessToken}" xmlns="http://eviware.com/soapui/config"/></con:setting></con:settings><con:endpoint>http://rest-api.upskills.in</con:endpoint><con:request>{
"firstname": "shipra",
"lastname": "jindal",
"email": "shiprajindal5@gmail.com",
"password": "password",
"confirm": "password", 
"telephone": "1-541-754-3010"
}</con:request><con:originalUri>http://rest-api.upskills.in/api/rest_admin/customers</con:originalUri><con:assertion type="Valid HTTP Status Codes" id="d2712c22-ec54-43b1-9877-e7ef00fd6efe" name="Valid HTTP Status Codes"><con:configuration><codes>200</codes></con:configuration></con:assertion><con:credentials><con:authType>No Authorization</con:authType></con:credentials><con:jmsConfig JMSDeliveryMode="PERSISTENT"/><con:jmsPropertyConfig/><con:parameters/></con:restRequest></con:config></con:testStep><con:testStep type="groovy" name="GSForID" id="557bcbc5-87b7-44b5-8968-1131015bfc3a"><con:settings/><con:config><script>import groovy.json.JsonSlurper
def response=testRunner.testCase.getTestStepByName("AddCustomer").getPropertyValue("response")
log.info response
def holder1 = new JsonSlurper().parseText(response)
def ID=holder1.data.id
log.info ID
testRunner.testCase.getTestStepByName("Properties").setPropertyValue("CustID",ID.toString())
</script></con:config></con:testStep><con:testStep type="restrequest" name="GetCustomerDetails" id="c8736c7c-7c1b-4351-a7a3-8c9b8e9c8987"><con:settings/><con:config service="http://rest-api.upskills.in" resourcePath="/api/rest_admin/customers/${Properties#CustID}" methodName="GetCustomerDetails" xsi:type="con:RestRequestStep" xmlns:xsi="http://www.w3.org/2001/XMLSchema-instance"><con:restRequest name="GetCustomerDetails" id="2874d57f-7ead-4396-94cb-422978ca4ff9" mediaType="application/json"><con:settings><con:setting id="com.eviware.soapui.impl.wsdl.WsdlRequest@request-headers">&lt;entry key="Authorization" value="${Properties#accessToken}" xmlns="http://eviware.com/soapui/config"/></con:setting></con:settings><con:endpoint>http://rest-api.upskills.in</con:endpoint><con:request/><con:originalUri>http://rest-api.upskills.in/api/rest_admin/customers/1597</con:originalUri><con:assertion type="Valid HTTP Status Codes" id="54c09d6b-0de6-41de-b9f6-a403cb5dbe46" name="Valid HTTP Status Codes"><con:configuration><codes>200</codes></con:configuration></con:assertion><con:credentials><con:authType>No Authorization</con:authType></con:credentials><con:jmsConfig JMSDeliveryMode="PERSISTENT"/><con:jmsPropertyConfig/><con:parameters/></con:restRequest></con:config></con:testStep><con:testStep type="restrequest" name="ModifyCustomerDetails" id="c7ca83d7-252e-43d6-a389-139ccbb6cbc9"><con:settings/><con:config service="http://rest-api.upskills.in" resourcePath="/api/rest_admin/customers/${Properties#CustID}" methodName="ModifyCustDetails" xsi:type="con:RestRequestStep" xmlns:xsi="http://www.w3.org/2001/XMLSchema-instance"><con:restRequest name="ModifyCustomerDetails" id="91ffd301-c8df-4a86-909a-0d2d7db75710" mediaType="application/json" postQueryString="false"><con:settings><con:setting id="com.eviware.soapui.impl.wsdl.WsdlRequest@request-headers">&lt;entry key="Authorization" value="${Properties#accessToken}" xmlns="http://eviware.com/soapui/config"/></con:setting></con:settings><con:endpoint>http://rest-api.upskills.in</con:endpoint><con:request>{
"firstname": "Krishna Kumar",
"telephone": "0123456789"
}</con:request><con:originalUri>http://rest-api.upskills.in/api/rest_admin/customers/1597</con:originalUri><con:assertion type="Valid HTTP Status Codes" id="5254ff29-525b-4222-8d0b-bb5b534d05d2" name="Valid HTTP Status Codes"><con:configuration><codes>200</codes></con:configuration></con:assertion><con:credentials><con:authType>No Authorization</con:authType></con:credentials><con:jmsConfig JMSDeliveryMode="PERSISTENT"/><con:jmsPropertyConfig/><con:parameters/></con:restRequest></con:config></con:testStep><con:testStep type="restrequest" name="GetCustomerDetailsAfterModify" id="4338c41e-e739-4eed-ac4d-5cdd71155ae7"><con:settings/><con:config service="http://rest-api.upskills.in" resourcePath="/api/rest_admin/customers/${Properties#CustID}" methodName="GetCustomerDetails" xsi:type="con:RestRequestStep" xmlns:xsi="http://www.w3.org/2001/XMLSchema-instance"><con:restRequest name="GetCustomerDetailsAfterModify" id="2874d57f-7ead-4396-94cb-422978ca4ff9" mediaType="application/json"><con:settings><con:setting id="com.eviware.soapui.impl.wsdl.WsdlRequest@request-headers">&lt;entry key="Authorization" value="${Properties#accessToken}" xmlns="http://eviware.com/soapui/config"/></con:setting></con:settings><con:endpoint>http://rest-api.upskills.in</con:endpoint><con:request/><con:originalUri>http://rest-api.upskills.in/api/rest_admin/customers/1597</con:originalUri><con:assertion type="Valid HTTP Status Codes" id="54c09d6b-0de6-41de-b9f6-a403cb5dbe46" name="Valid HTTP Status Codes"><con:configuration><codes>200</codes></con:configuration></con:assertion><con:assertion type="GroovyScriptAssertion" id="25c1eba0-5d43-4e62-8899-a6509a58269d" name="Script Assertion"><con:configuration><scriptText>import groovy.json.JsonSlurper
def response=messageExchange.response.responseContent
def holder =new JsonSlurper().parseText(response)

def firstname= holder.data.firstname
//log.info firstname
assert firstname=="Krishna Kumar"
assert holder.data.telephone=="0123456789"
</scriptText></con:configuration></con:assertion><con:credentials><con:authType>No Authorization</con:authType></con:credentials><con:jmsConfig JMSDeliveryMode="PERSISTENT"/><con:jmsPropertyConfig/><con:parameters/></con:restRequest></con:config></con:testStep><con:properties><con:property><con:name>id</con:name><con:value>Doe</con:value></con:property></con:properties></con:testCase><con:properties><con:property><con:name>id</con:name><con:value/></con:property></con:properties></con:testSuite><con:properties/><con:wssContainer/><con:oAuth2ProfileContainer/><con:oAuth1ProfileContainer/></con:soapui-project>